data_tracking/__init__.py
data_tracking/connection.py
data_tracking/dicom_import.py
data_tracking/files_recording.py
data_tracking/nifti_import.py
data_tracking/others_import.py
data_tracking/utils.py
data_tracking-1.7.3.dist-info/DESCRIPTION.rst
data_tracking-1.7.3.dist-info/METADATA
data_tracking-1.7.3.dist-info/RECORD
data_tracking-1.7.3.dist-info/WHEEL
data_tracking-1.7.3.dist-info/metadata.json
data_tracking-1.7.3.dist-info/top_level.txt
