Metadata-Version: 2.0
Name: data-tracking
Version: 1.7.3
Summary: Extract meta-data from DICOM and NIFTI files
Home-page: https://github.com/LREN-CHUV/data-tracking
Author: Mirco Nasuti
Author-email: mirco.nasuti@chuv.ch
License: Apache 2.0
Keywords: mri dicom nifti
Platform: UNKNOWN
Classifier: Intended Audience :: Developers
Classifier: Intended Audience :: Science/Research
Classifier: Operating System :: Unix
Classifier: License :: OSI Approved :: Apache Software License
Classifier: Topic :: Scientific/Engineering :: Bio-Informatics
Classifier: Programming Language :: Python :: 3 :: Only
Classifier: Programming Language :: Python :: 3.4
Classifier: Programming Language :: Python :: 3.5
Classifier: Programming Language :: Python :: 3.6
Requires-Dist: apache-airflow (==1.9.0)
Requires-Dist: nibabel (>=2.1.0)
Requires-Dist: psycopg2-binary (==2.7.4)
Requires-Dist: pydicom (==0.9.9)
Requires-Dist: python-magic (>=0.4.12)
Requires-Dist: sqlalchemy (==1.2.5)
